{
  "C:\\Users\\B\\OneDrive - Clear Path solutions DBA Flash funding Solutions\\Desktop\\FLASH DASH v0.9\\flashdash-backend\\serverless.yml": {
    "versionFramework": "4.17.1",
    "servicePath": "C:\\Users\\B\\OneDrive - Clear Path solutions DBA Flash funding Solutions\\Desktop\\FLASH DASH v0.9\\flashdash-backend\\serverless.yml",
    "serviceConfigFileName": "serverless.yml",
    "service": {
      "service": "flashdash-backend",
      "provider": {
        "name": "aws",
        "runtime": "nodejs18.x",
        "region": "us-east-1",
        "timeout": 29,
        "environment": {
          "JWT_SECRET": "<REDACTED>",
          "DB_URL": "postgresql://postgres.dxrbrhfhpzurrjwbhxhw:DBpass%40123456%21@aws-0-us-east-1.pooler.supabase.com:5432/postgres",
          "FORTH_API_SECRET": "<REDACTED>",
          "FORTH_API_CLIENT_ID": "10027",
          "PORT": "4000",
          "DATABASE_URL": "postgresql://postgres.dxrbrhfhpzurrjwbhxhw:DBpass%40123456%21@aws-0-us-east-1.pooler.supabase.com:5432/postgres"
        },
        "stage": "dev",
        "versionFunctions": true,
        "compiledCloudFormationTemplate": {
          "AWSTemplateFormatVersion": "2010-09-09",
          "Description": "The AWS CloudFormation template for this Serverless application",
          "Resources": {
            "ApiLogGroup": {
              "Type": "AWS::Logs::LogGroup",
              "Properties": {
                "LogGroupName": "/aws/lambda/flashdash-backend-dev-api"
              }
            },
            "IamRoleLambdaExecution": {
              "Type": "AWS::IAM::Role",
              "Properties": {
                "AssumeRolePolicyDocument": {
                  "Version": "2012-10-17",
                  "Statement": [
                    {
                      "Effect": "Allow",
                      "Principal": {
                        "Service": [
                          "lambda.amazonaws.com"
                        ]
                      },
                      "Action": [
                        "sts:AssumeRole"
                      ]
                    }
                  ]
                },
                "Policies": [
                  {
                    "PolicyName": {
                      "Fn::Join": [
                        "-",
                        [
                          "flashdash-backend",
                          "dev",
                          "lambda"
                        ]
                      ]
                    },
                    "PolicyDocument": {
                      "Version": "2012-10-17",
                      "Statement": [
                        {
                          "Effect": "Allow",
                          "Action": [
                            "logs:CreateLogStream",
                            "logs:CreateLogGroup",
                            "logs:TagResource"
                          ],
                          "Resource": [
                            {
                              "Fn::Sub": "arn:${AWS::Partition}:logs:${AWS::Region}:${AWS::AccountId}:log-group:/aws/lambda/flashdash-backend-dev*:*"
                            }
                          ]
                        },
                        {
                          "Effect": "Allow",
                          "Action": [
                            "logs:PutLogEvents"
                          ],
                          "Resource": [
                            {
                              "Fn::Sub": "arn:${AWS::Partition}:logs:${AWS::Region}:${AWS::AccountId}:log-group:/aws/lambda/flashdash-backend-dev*:*:*"
                            }
                          ]
                        }
                      ]
                    }
                  }
                ],
                "Path": "/",
                "RoleName": {
                  "Fn::Join": [
                    "-",
                    [
                      "flashdash-backend",
                      "dev",
                      {
                        "Ref": "AWS::Region"
                      },
                      "lambdaRole"
                    ]
                  ]
                }
              }
            },
            "ApiLambdaFunction": {
              "Type": "AWS::Lambda::Function",
              "Properties": {
                "Code": {
                  "S3Bucket": "serverless-framework-deployments-us-east-1-dfa1c07b-f991",
                  "S3Key": "serverless/flashdash-backend/dev/1751188896642-2025-06-29T09:21:36.642Z/flashdash-backend.zip"
                },
                "Handler": "server.handler",
                "Runtime": "nodejs18.x",
                "FunctionName": "flashdash-backend-dev-api",
                "MemorySize": 1024,
                "Timeout": 29,
                "Environment": {
                  "Variables": {
                    "JWT_SECRET": "<REDACTED>",
                    "DB_URL": "postgresql://postgres.dxrbrhfhpzurrjwbhxhw:DBpass%40123456%21@aws-0-us-east-1.pooler.supabase.com:5432/postgres",
                    "FORTH_API_SECRET": "<REDACTED>",
                    "FORTH_API_CLIENT_ID": "10027",
                    "PORT": "4000",
                    "DATABASE_URL": "postgresql://postgres.dxrbrhfhpzurrjwbhxhw:DBpass%40123456%21@aws-0-us-east-1.pooler.supabase.com:5432/postgres"
                  }
                },
                "Role": {
                  "Fn::GetAtt": [
                    "IamRoleLambdaExecution",
                    "Arn"
                  ]
                }
              },
              "DependsOn": [
                "ApiLogGroup"
              ]
            },
            "ApiLambdaVersionnIg7rUSI5PI9frwc5assAh5NvKEkEmlFYrnKGATxM": {
              "Type": "AWS::Lambda::Version",
              "DeletionPolicy": "Retain",
              "Properties": {
                "FunctionName": {
                  "Ref": "ApiLambdaFunction"
                },
                "CodeSha256": "hmEwFylYM3vD4kTD5F6/8Mk8Ibry7FndlvdtGicy7kc="
              }
            },
            "ApiGatewayRestApi": {
              "Type": "AWS::ApiGateway::RestApi",
              "Properties": {
                "Name": "dev-flashdash-backend",
                "EndpointConfiguration": {
                  "Types": [
                    "EDGE"
                  ]
                },
                "Policy": ""
              }
            },
            "ApiGatewayResourceProxyVar": {
              "Type": "AWS::ApiGateway::Resource",
              "Properties": {
                "ParentId": {
                  "Fn::GetAtt": [
                    "ApiGatewayRestApi",
                    "RootResourceId"
                  ]
                },
                "PathPart": "{proxy+}",
                "RestApiId": {
                  "Ref": "ApiGatewayRestApi"
                }
              }
            },
            "ApiGatewayMethodProxyVarOptions": {
              "Type": "AWS::ApiGateway::Method",
              "Properties": {
                "AuthorizationType": "NONE",
                "HttpMethod": "OPTIONS",
                "MethodResponses": [
                  {
                    "StatusCode": "200",
                    "ResponseParameters": {
                      "method.response.header.Access-Control-Allow-Origin": true,
                      "method.response.header.Access-Control-Allow-Headers": true,
                      "method.response.header.Access-Control-Allow-Methods": true
                    },
                    "ResponseModels": {}
                  }
                ],
                "RequestParameters": {},
                "Integration": {
                  "Type": "MOCK",
                  "RequestTemplates": {
                    "application/json": "{statusCode:200}"
                  },
                  "ContentHandling": "CONVERT_TO_TEXT",
                  "IntegrationResponses": [
                    {
                      "StatusCode": "200",
                      "ResponseParameters": {
                        "method.response.header.Access-Control-Allow-Origin": "'*'",
                        "method.response.header.Access-Control-Allow-Headers": "'Content-Type,X-Amz-Date,Authorization,X-Api-Key,X-Amz-Security-Token,X-Amz-User-Agent,X-Amzn-Trace-Id'",
                        "method.response.header.Access-Control-Allow-Methods": "'OPTIONS,DELETE,GET,HEAD,PATCH,POST,PUT'"
                      },
                      "ResponseTemplates": {
                        "application/json": ""
                      }
                    }
                  ]
                },
                "ResourceId": {
                  "Ref": "ApiGatewayResourceProxyVar"
                },
                "RestApiId": {
                  "Ref": "ApiGatewayRestApi"
                }
              }
            },
            "ApiGatewayMethodProxyVarAny": {
              "Type": "AWS::ApiGateway::Method",
              "Properties": {
                "HttpMethod": "ANY",
                "RequestParameters": {},
                "ResourceId": {
                  "Ref": "ApiGatewayResourceProxyVar"
                },
                "RestApiId": {
                  "Ref": "ApiGatewayRestApi"
                },
                "ApiKeyRequired": "<REDACTED>",
                "AuthorizationType": "NONE",
                "Integration": {
                  "IntegrationHttpMethod": "POST",
                  "Type": "AWS_PROXY",
                  "Uri": {
                    "Fn::Join": [
                      "",
                      [
                        "arn:",
                        {
                          "Ref": "AWS::Partition"
                        },
                        ":apigateway:",
                        {
                          "Ref": "AWS::Region"
                        },
                        ":lambda:path/2015-03-31/functions/",
                        {
                          "Fn::GetAtt": [
                            "ApiLambdaFunction",
                            "Arn"
                          ]
                        },
                        "/invocations"
                      ]
                    ]
                  }
                },
                "MethodResponses": []
              },
              "DependsOn": [
                "ApiLambdaPermissionApiGateway"
              ]
            },
            "ApiGatewayDeployment1751188881856": {
              "Type": "AWS::ApiGateway::Deployment",
              "Properties": {
                "RestApiId": {
                  "Ref": "ApiGatewayRestApi"
                },
                "StageName": "dev"
              },
              "DependsOn": [
                "ApiGatewayMethodProxyVarOptions",
                "ApiGatewayMethodProxyVarAny"
              ]
            },
            "ApiLambdaPermissionApiGateway": {
              "Type": "AWS::Lambda::Permission",
              "Properties": {
                "FunctionName": {
                  "Fn::GetAtt": [
                    "ApiLambdaFunction",
                    "Arn"
                  ]
                },
                "Action": "lambda:InvokeFunction",
                "Principal": "apigateway.amazonaws.com",
                "SourceArn": {
                  "Fn::Join": [
                    "",
                    [
                      "arn:",
                      {
                        "Ref": "AWS::Partition"
                      },
                      ":execute-api:",
                      {
                        "Ref": "AWS::Region"
                      },
                      ":",
                      {
                        "Ref": "AWS::AccountId"
                      },
                      ":",
                      {
                        "Ref": "ApiGatewayRestApi"
                      },
                      "/*/*"
                    ]
                  ]
                }
              }
            }
          },
          "Outputs": {
            "ServerlessDeploymentBucketName": {
              "Value": "serverless-framework-deployments-us-east-1-dfa1c07b-f991",
              "Export": {
                "Name": "sls-flashdash-backend-dev-ServerlessDeploymentBucketName"
              }
            },
            "ApiLambdaFunctionQualifiedArn": {
              "Description": "Current Lambda function version",
              "Value": {
                "Ref": "ApiLambdaVersionnIg7rUSI5PI9frwc5assAh5NvKEkEmlFYrnKGATxM"
              },
              "Export": {
                "Name": "sls-flashdash-backend-dev-ApiLambdaFunctionQualifiedArn"
              }
            },
            "ServiceEndpoint": {
              "Description": "URL of the service endpoint",
              "Value": {
                "Fn::Join": [
                  "",
                  [
                    "https://",
                    {
                      "Ref": "ApiGatewayRestApi"
                    },
                    ".execute-api.",
                    {
                      "Ref": "AWS::Region"
                    },
                    ".",
                    {
                      "Ref": "AWS::URLSuffix"
                    },
                    "/dev"
                  ]
                ]
              },
              "Export": {
                "Name": "sls-flashdash-backend-dev-ServiceEndpoint"
              }
            }
          }
        },
        "vpc": {}
      },
      "functions": {
        "api": {
          "handler": "server.handler",
          "events": [
            {
              "http": {
                "path": "{proxy+}",
                "method": "any",
                "cors": {
                  "origin": "*",
                  "methods": [
                    "OPTIONS",
                    "ANY"
                  ],
                  "headers": [
                    "Content-Type",
                    "X-Amz-Date",
                    "Authorization",
                    "X-Api-Key",
                    "X-Amz-Security-Token",
                    "X-Amz-User-Agent",
                    "X-Amzn-Trace-Id"
                  ],
                  "allowCredentials": "<REDACTED>"
                },
                "integration": "AWS_PROXY"
              }
            }
          ],
          "name": "flashdash-backend-dev-api",
          "package": {},
          "memory": 1024,
          "timeout": 29,
          "runtime": "nodejs18.x",
          "vpc": {},
          "versionLogicalId": "ApiLambdaVersionnIg7rUSI5PI9frwc5assAh5NvKEkEmlFYrnKGATxM"
        }
      },
      "plugins": [
        "serverless-offline",
        "serverless-dotenv-plugin"
      ],
      "package": {
        "exclude": [
          ".gitignore",
          "README.md",
          "createAdmin.js"
        ],
        "artifactsS3KeyDirname": "serverless/flashdash-backend/dev/code-artifacts",
        "deploymentBucket": "serverless-framework-deployments-us-east-1-dfa1c07b-f991",
        "artifact": "C:\\Users\\B\\OneDrive - Clear Path solutions DBA Flash funding Solutions\\Desktop\\FLASH DASH v0.9\\flashdash-backend\\.serverless\\flashdash-backend.zip",
        "artifactDirectoryName": "serverless/flashdash-backend/dev/1751188896642-2025-06-29T09:21:36.642Z"
      }
    },
    "provider": {
      "name": "aws",
      "runtime": "nodejs18.x",
      "region": "us-east-1",
      "timeout": 29,
      "environment": {
        "JWT_SECRET": "<REDACTED>",
        "DB_URL": "postgresql://postgres.dxrbrhfhpzurrjwbhxhw:DBpass%40123456%21@aws-0-us-east-1.pooler.supabase.com:5432/postgres",
        "FORTH_API_SECRET": "<REDACTED>",
        "FORTH_API_CLIENT_ID": "10027",
        "PORT": "4000",
        "DATABASE_URL": "postgresql://postgres.dxrbrhfhpzurrjwbhxhw:DBpass%40123456%21@aws-0-us-east-1.pooler.supabase.com:5432/postgres"
      },
      "stage": "dev",
      "versionFunctions": true,
      "compiledCloudFormationTemplate": {
        "AWSTemplateFormatVersion": "2010-09-09",
        "Description": "The AWS CloudFormation template for this Serverless application",
        "Resources": {
          "ApiLogGroup": {
            "Type": "AWS::Logs::LogGroup",
            "Properties": {
              "LogGroupName": "/aws/lambda/flashdash-backend-dev-api"
            }
          },
          "IamRoleLambdaExecution": {
            "Type": "AWS::IAM::Role",
            "Properties": {
              "AssumeRolePolicyDocument": {
                "Version": "2012-10-17",
                "Statement": [
                  {
                    "Effect": "Allow",
                    "Principal": {
                      "Service": [
                        "lambda.amazonaws.com"
                      ]
                    },
                    "Action": [
                      "sts:AssumeRole"
                    ]
                  }
                ]
              },
              "Policies": [
                {
                  "PolicyName": {
                    "Fn::Join": [
                      "-",
                      [
                        "flashdash-backend",
                        "dev",
                        "lambda"
                      ]
                    ]
                  },
                  "PolicyDocument": {
                    "Version": "2012-10-17",
                    "Statement": [
                      {
                        "Effect": "Allow",
                        "Action": [
                          "logs:CreateLogStream",
                          "logs:CreateLogGroup",
                          "logs:TagResource"
                        ],
                        "Resource": [
                          {
                            "Fn::Sub": "arn:${AWS::Partition}:logs:${AWS::Region}:${AWS::AccountId}:log-group:/aws/lambda/flashdash-backend-dev*:*"
                          }
                        ]
                      },
                      {
                        "Effect": "Allow",
                        "Action": [
                          "logs:PutLogEvents"
                        ],
                        "Resource": [
                          {
                            "Fn::Sub": "arn:${AWS::Partition}:logs:${AWS::Region}:${AWS::AccountId}:log-group:/aws/lambda/flashdash-backend-dev*:*:*"
                          }
                        ]
                      }
                    ]
                  }
                }
              ],
              "Path": "/",
              "RoleName": {
                "Fn::Join": [
                  "-",
                  [
                    "flashdash-backend",
                    "dev",
                    {
                      "Ref": "AWS::Region"
                    },
                    "lambdaRole"
                  ]
                ]
              }
            }
          },
          "ApiLambdaFunction": {
            "Type": "AWS::Lambda::Function",
            "Properties": {
              "Code": {
                "S3Bucket": "serverless-framework-deployments-us-east-1-dfa1c07b-f991",
                "S3Key": "serverless/flashdash-backend/dev/1751188896642-2025-06-29T09:21:36.642Z/flashdash-backend.zip"
              },
              "Handler": "server.handler",
              "Runtime": "nodejs18.x",
              "FunctionName": "flashdash-backend-dev-api",
              "MemorySize": 1024,
              "Timeout": 29,
              "Environment": {
                "Variables": {
                  "JWT_SECRET": "<REDACTED>",
                  "DB_URL": "postgresql://postgres.dxrbrhfhpzurrjwbhxhw:DBpass%40123456%21@aws-0-us-east-1.pooler.supabase.com:5432/postgres",
                  "FORTH_API_SECRET": "<REDACTED>",
                  "FORTH_API_CLIENT_ID": "10027",
                  "PORT": "4000",
                  "DATABASE_URL": "postgresql://postgres.dxrbrhfhpzurrjwbhxhw:DBpass%40123456%21@aws-0-us-east-1.pooler.supabase.com:5432/postgres"
                }
              },
              "Role": {
                "Fn::GetAtt": [
                  "IamRoleLambdaExecution",
                  "Arn"
                ]
              }
            },
            "DependsOn": [
              "ApiLogGroup"
            ]
          },
          "ApiLambdaVersionnIg7rUSI5PI9frwc5assAh5NvKEkEmlFYrnKGATxM": {
            "Type": "AWS::Lambda::Version",
            "DeletionPolicy": "Retain",
            "Properties": {
              "FunctionName": {
                "Ref": "ApiLambdaFunction"
              },
              "CodeSha256": "hmEwFylYM3vD4kTD5F6/8Mk8Ibry7FndlvdtGicy7kc="
            }
          },
          "ApiGatewayRestApi": {
            "Type": "AWS::ApiGateway::RestApi",
            "Properties": {
              "Name": "dev-flashdash-backend",
              "EndpointConfiguration": {
                "Types": [
                  "EDGE"
                ]
              },
              "Policy": ""
            }
          },
          "ApiGatewayResourceProxyVar": {
            "Type": "AWS::ApiGateway::Resource",
            "Properties": {
              "ParentId": {
                "Fn::GetAtt": [
                  "ApiGatewayRestApi",
                  "RootResourceId"
                ]
              },
              "PathPart": "{proxy+}",
              "RestApiId": {
                "Ref": "ApiGatewayRestApi"
              }
            }
          },
          "ApiGatewayMethodProxyVarOptions": {
            "Type": "AWS::ApiGateway::Method",
            "Properties": {
              "AuthorizationType": "NONE",
              "HttpMethod": "OPTIONS",
              "MethodResponses": [
                {
                  "StatusCode": "200",
                  "ResponseParameters": {
                    "method.response.header.Access-Control-Allow-Origin": true,
                    "method.response.header.Access-Control-Allow-Headers": true,
                    "method.response.header.Access-Control-Allow-Methods": true
                  },
                  "ResponseModels": {}
                }
              ],
              "RequestParameters": {},
              "Integration": {
                "Type": "MOCK",
                "RequestTemplates": {
                  "application/json": "{statusCode:200}"
                },
                "ContentHandling": "CONVERT_TO_TEXT",
                "IntegrationResponses": [
                  {
                    "StatusCode": "200",
                    "ResponseParameters": {
                      "method.response.header.Access-Control-Allow-Origin": "'*'",
                      "method.response.header.Access-Control-Allow-Headers": "'Content-Type,X-Amz-Date,Authorization,X-Api-Key,X-Amz-Security-Token,X-Amz-User-Agent,X-Amzn-Trace-Id'",
                      "method.response.header.Access-Control-Allow-Methods": "'OPTIONS,DELETE,GET,HEAD,PATCH,POST,PUT'"
                    },
                    "ResponseTemplates": {
                      "application/json": ""
                    }
                  }
                ]
              },
              "ResourceId": {
                "Ref": "ApiGatewayResourceProxyVar"
              },
              "RestApiId": {
                "Ref": "ApiGatewayRestApi"
              }
            }
          },
          "ApiGatewayMethodProxyVarAny": {
            "Type": "AWS::ApiGateway::Method",
            "Properties": {
              "HttpMethod": "ANY",
              "RequestParameters": {},
              "ResourceId": {
                "Ref": "ApiGatewayResourceProxyVar"
              },
              "RestApiId": {
                "Ref": "ApiGatewayRestApi"
              },
              "ApiKeyRequired": "<REDACTED>",
              "AuthorizationType": "NONE",
              "Integration": {
                "IntegrationHttpMethod": "POST",
                "Type": "AWS_PROXY",
                "Uri": {
                  "Fn::Join": [
                    "",
                    [
                      "arn:",
                      {
                        "Ref": "AWS::Partition"
                      },
                      ":apigateway:",
                      {
                        "Ref": "AWS::Region"
                      },
                      ":lambda:path/2015-03-31/functions/",
                      {
                        "Fn::GetAtt": [
                          "ApiLambdaFunction",
                          "Arn"
                        ]
                      },
                      "/invocations"
                    ]
                  ]
                }
              },
              "MethodResponses": []
            },
            "DependsOn": [
              "ApiLambdaPermissionApiGateway"
            ]
          },
          "ApiGatewayDeployment1751188881856": {
            "Type": "AWS::ApiGateway::Deployment",
            "Properties": {
              "RestApiId": {
                "Ref": "ApiGatewayRestApi"
              },
              "StageName": "dev"
            },
            "DependsOn": [
              "ApiGatewayMethodProxyVarOptions",
              "ApiGatewayMethodProxyVarAny"
            ]
          },
          "ApiLambdaPermissionApiGateway": {
            "Type": "AWS::Lambda::Permission",
            "Properties": {
              "FunctionName": {
                "Fn::GetAtt": [
                  "ApiLambdaFunction",
                  "Arn"
                ]
              },
              "Action": "lambda:InvokeFunction",
              "Principal": "apigateway.amazonaws.com",
              "SourceArn": {
                "Fn::Join": [
                  "",
                  [
                    "arn:",
                    {
                      "Ref": "AWS::Partition"
                    },
                    ":execute-api:",
                    {
                      "Ref": "AWS::Region"
                    },
                    ":",
                    {
                      "Ref": "AWS::AccountId"
                    },
                    ":",
                    {
                      "Ref": "ApiGatewayRestApi"
                    },
                    "/*/*"
                  ]
                ]
              }
            }
          }
        },
        "Outputs": {
          "ServerlessDeploymentBucketName": {
            "Value": "serverless-framework-deployments-us-east-1-dfa1c07b-f991",
            "Export": {
              "Name": "sls-flashdash-backend-dev-ServerlessDeploymentBucketName"
            }
          },
          "ApiLambdaFunctionQualifiedArn": {
            "Description": "Current Lambda function version",
            "Value": {
              "Ref": "ApiLambdaVersionnIg7rUSI5PI9frwc5assAh5NvKEkEmlFYrnKGATxM"
            },
            "Export": {
              "Name": "sls-flashdash-backend-dev-ApiLambdaFunctionQualifiedArn"
            }
          },
          "ServiceEndpoint": {
            "Description": "URL of the service endpoint",
            "Value": {
              "Fn::Join": [
                "",
                [
                  "https://",
                  {
                    "Ref": "ApiGatewayRestApi"
                  },
                  ".execute-api.",
                  {
                    "Ref": "AWS::Region"
                  },
                  ".",
                  {
                    "Ref": "AWS::URLSuffix"
                  },
                  "/dev"
                ]
              ]
            },
            "Export": {
              "Name": "sls-flashdash-backend-dev-ServiceEndpoint"
            }
          }
        }
      },
      "vpc": {}
    },
    "dashboard": {
      "isEnabledForService": false,
      "requiredAuthentication": false,
      "orgFeaturesInUse": null,
      "orgObservabilityIntegrations": null,
      "serviceAppId": null,
      "serviceProvider": null,
      "instanceParameters": null
    },
    "serviceRawFile": "service: flashdash-backend\r\n\r\nprovider:\r\n  name: aws\r\n  runtime: nodejs18.x\r\n  region: us-east-1\r\n  timeout: 29 # To match API Gateway max timeout\r\n  environment:\r\n    JWT_SECRET: ${env:JWT_SECRET}\r\n    DB_URL: ${env:DATABASE_URL}\r\n    FORTH_API_SECRET: ${env:FORTH_API_SECRET}\r\n    FORTH_API_CLIENT_ID: ${env:FORTH_API_CLIENT_ID}\r\n\r\nfunctions:\r\n  api:\r\n    handler: server.handler\r\n    events:\r\n      - http:\r\n          path: /{proxy+}\r\n          method: any\r\n          cors: true\r\n\r\nplugins:\r\n  - serverless-offline\r\n  - serverless-dotenv-plugin\r\n\r\npackage:\r\n  exclude:\r\n    - .gitignore\r\n    - README.md\r\n    - createAdmin.js\r\n",
    "command": [
      "deploy"
    ],
    "options": {},
    "orgId": "a8de0dcb-6001-4830-9644-d38adb986602",
    "orgName": "ffsbackend",
    "userId": "BQLFsmdDx4QMRgKgnz",
    "userName": "ffsbackend",
    "serviceProviderAwsAccountId": "400344123851",
    "serviceProviderAwsCfStackName": "flashdash-backend-dev",
    "serviceProviderAwsCfStackId": "arn:aws:cloudformation:us-east-1:400344123851:stack/flashdash-backend-dev/a659f1f0-54bd-11f0-a755-0affd8a1a035",
    "serviceProviderAwsCfStackCreated": "2025-06-29T07:49:56.658Z",
    "serviceProviderAwsCfStackUpdated": "2025-06-29T08:53:21.425Z",
    "serviceProviderAwsCfStackStatus": "UPDATE_COMPLETE",
    "serviceProviderAwsCfStackOutputs": [
      {
        "OutputKey": "ApiLambdaFunctionQualifiedArn",
        "OutputValue": "arn:aws:lambda:us-east-1:400344123851:function:flashdash-backend-dev-api:8",
        "Description": "Current Lambda function version",
        "ExportName": "sls-flashdash-backend-dev-ApiLambdaFunctionQualifiedArn"
      },
      {
        "OutputKey": "ServiceEndpoint",
        "OutputValue": "https://1813b6ckkf.execute-api.us-east-1.amazonaws.com/dev",
        "Description": "URL of the service endpoint",
        "ExportName": "sls-flashdash-backend-dev-ServiceEndpoint"
      },
      {
        "OutputKey": "ServerlessDeploymentBucketName",
        "OutputValue": "serverless-framework-deployments-us-east-1-dfa1c07b-f991",
        "ExportName": "sls-flashdash-backend-dev-ServerlessDeploymentBucketName"
      }
    ],
    "compiledCloudFormationTemplate": {
      "AWSTemplateFormatVersion": "2010-09-09",
      "Description": "The AWS CloudFormation template for this Serverless application",
      "Resources": {
        "ApiLogGroup": {
          "Type": "AWS::Logs::LogGroup",
          "Properties": {
            "LogGroupName": "/aws/lambda/flashdash-backend-dev-api"
          }
        },
        "IamRoleLambdaExecution": {
          "Type": "AWS::IAM::Role",
          "Properties": {
            "AssumeRolePolicyDocument": {
              "Version": "2012-10-17",
              "Statement": [
                {
                  "Effect": "Allow",
                  "Principal": {
                    "Service": [
                      "lambda.amazonaws.com"
                    ]
                  },
                  "Action": [
                    "sts:AssumeRole"
                  ]
                }
              ]
            },
            "Policies": [
              {
                "PolicyName": {
                  "Fn::Join": [
                    "-",
                    [
                      "flashdash-backend",
                      "dev",
                      "lambda"
                    ]
                  ]
                },
                "PolicyDocument": {
                  "Version": "2012-10-17",
                  "Statement": [
                    {
                      "Effect": "Allow",
                      "Action": [
                        "logs:CreateLogStream",
                        "logs:CreateLogGroup",
                        "logs:TagResource"
                      ],
                      "Resource": [
                        {
                          "Fn::Sub": "arn:${AWS::Partition}:logs:${AWS::Region}:${AWS::AccountId}:log-group:/aws/lambda/flashdash-backend-dev*:*"
                        }
                      ]
                    },
                    {
                      "Effect": "Allow",
                      "Action": [
                        "logs:PutLogEvents"
                      ],
                      "Resource": [
                        {
                          "Fn::Sub": "arn:${AWS::Partition}:logs:${AWS::Region}:${AWS::AccountId}:log-group:/aws/lambda/flashdash-backend-dev*:*:*"
                        }
                      ]
                    }
                  ]
                }
              }
            ],
            "Path": "/",
            "RoleName": {
              "Fn::Join": [
                "-",
                [
                  "flashdash-backend",
                  "dev",
                  {
                    "Ref": "AWS::Region"
                  },
                  "lambdaRole"
                ]
              ]
            }
          }
        },
        "ApiLambdaFunction": {
          "Type": "AWS::Lambda::Function",
          "Properties": {
            "Code": {
              "S3Bucket": "serverless-framework-deployments-us-east-1-dfa1c07b-f991",
              "S3Key": "serverless/flashdash-backend/dev/1751188896642-2025-06-29T09:21:36.642Z/flashdash-backend.zip"
            },
            "Handler": "server.handler",
            "Runtime": "nodejs18.x",
            "FunctionName": "flashdash-backend-dev-api",
            "MemorySize": 1024,
            "Timeout": 29,
            "Environment": {
              "Variables": {
                "JWT_SECRET": "<REDACTED>",
                "DB_URL": "postgresql://postgres.dxrbrhfhpzurrjwbhxhw:DBpass%40123456%21@aws-0-us-east-1.pooler.supabase.com:5432/postgres",
                "FORTH_API_SECRET": "<REDACTED>",
                "FORTH_API_CLIENT_ID": "10027",
                "PORT": "4000",
                "DATABASE_URL": "postgresql://postgres.dxrbrhfhpzurrjwbhxhw:DBpass%40123456%21@aws-0-us-east-1.pooler.supabase.com:5432/postgres"
              }
            },
            "Role": {
              "Fn::GetAtt": [
                "IamRoleLambdaExecution",
                "Arn"
              ]
            }
          },
          "DependsOn": [
            "ApiLogGroup"
          ]
        },
        "ApiLambdaVersionnIg7rUSI5PI9frwc5assAh5NvKEkEmlFYrnKGATxM": {
          "Type": "AWS::Lambda::Version",
          "DeletionPolicy": "Retain",
          "Properties": {
            "FunctionName": {
              "Ref": "ApiLambdaFunction"
            },
            "CodeSha256": "hmEwFylYM3vD4kTD5F6/8Mk8Ibry7FndlvdtGicy7kc="
          }
        },
        "ApiGatewayRestApi": {
          "Type": "AWS::ApiGateway::RestApi",
          "Properties": {
            "Name": "dev-flashdash-backend",
            "EndpointConfiguration": {
              "Types": [
                "EDGE"
              ]
            },
            "Policy": ""
          }
        },
        "ApiGatewayResourceProxyVar": {
          "Type": "AWS::ApiGateway::Resource",
          "Properties": {
            "ParentId": {
              "Fn::GetAtt": [
                "ApiGatewayRestApi",
                "RootResourceId"
              ]
            },
            "PathPart": "{proxy+}",
            "RestApiId": {
              "Ref": "ApiGatewayRestApi"
            }
          }
        },
        "ApiGatewayMethodProxyVarOptions": {
          "Type": "AWS::ApiGateway::Method",
          "Properties": {
            "AuthorizationType": "NONE",
            "HttpMethod": "OPTIONS",
            "MethodResponses": [
              {
                "StatusCode": "200",
                "ResponseParameters": {
                  "method.response.header.Access-Control-Allow-Origin": true,
                  "method.response.header.Access-Control-Allow-Headers": true,
                  "method.response.header.Access-Control-Allow-Methods": true
                },
                "ResponseModels": {}
              }
            ],
            "RequestParameters": {},
            "Integration": {
              "Type": "MOCK",
              "RequestTemplates": {
                "application/json": "{statusCode:200}"
              },
              "ContentHandling": "CONVERT_TO_TEXT",
              "IntegrationResponses": [
                {
                  "StatusCode": "200",
                  "ResponseParameters": {
                    "method.response.header.Access-Control-Allow-Origin": "'*'",
                    "method.response.header.Access-Control-Allow-Headers": "'Content-Type,X-Amz-Date,Authorization,X-Api-Key,X-Amz-Security-Token,X-Amz-User-Agent,X-Amzn-Trace-Id'",
                    "method.response.header.Access-Control-Allow-Methods": "'OPTIONS,DELETE,GET,HEAD,PATCH,POST,PUT'"
                  },
                  "ResponseTemplates": {
                    "application/json": ""
                  }
                }
              ]
            },
            "ResourceId": {
              "Ref": "ApiGatewayResourceProxyVar"
            },
            "RestApiId": {
              "Ref": "ApiGatewayRestApi"
            }
          }
        },
        "ApiGatewayMethodProxyVarAny": {
          "Type": "AWS::ApiGateway::Method",
          "Properties": {
            "HttpMethod": "ANY",
            "RequestParameters": {},
            "ResourceId": {
              "Ref": "ApiGatewayResourceProxyVar"
            },
            "RestApiId": {
              "Ref": "ApiGatewayRestApi"
            },
            "ApiKeyRequired": "<REDACTED>",
            "AuthorizationType": "NONE",
            "Integration": {
              "IntegrationHttpMethod": "POST",
              "Type": "AWS_PROXY",
              "Uri": {
                "Fn::Join": [
                  "",
                  [
                    "arn:",
                    {
                      "Ref": "AWS::Partition"
                    },
                    ":apigateway:",
                    {
                      "Ref": "AWS::Region"
                    },
                    ":lambda:path/2015-03-31/functions/",
                    {
                      "Fn::GetAtt": [
                        "ApiLambdaFunction",
                        "Arn"
                      ]
                    },
                    "/invocations"
                  ]
                ]
              }
            },
            "MethodResponses": []
          },
          "DependsOn": [
            "ApiLambdaPermissionApiGateway"
          ]
        },
        "ApiGatewayDeployment1751188881856": {
          "Type": "AWS::ApiGateway::Deployment",
          "Properties": {
            "RestApiId": {
              "Ref": "ApiGatewayRestApi"
            },
            "StageName": "dev"
          },
          "DependsOn": [
            "ApiGatewayMethodProxyVarOptions",
            "ApiGatewayMethodProxyVarAny"
          ]
        },
        "ApiLambdaPermissionApiGateway": {
          "Type": "AWS::Lambda::Permission",
          "Properties": {
            "FunctionName": {
              "Fn::GetAtt": [
                "ApiLambdaFunction",
                "Arn"
              ]
            },
            "Action": "lambda:InvokeFunction",
            "Principal": "apigateway.amazonaws.com",
            "SourceArn": {
              "Fn::Join": [
                "",
                [
                  "arn:",
                  {
                    "Ref": "AWS::Partition"
                  },
                  ":execute-api:",
                  {
                    "Ref": "AWS::Region"
                  },
                  ":",
                  {
                    "Ref": "AWS::AccountId"
                  },
                  ":",
                  {
                    "Ref": "ApiGatewayRestApi"
                  },
                  "/*/*"
                ]
              ]
            }
          }
        }
      },
      "Outputs": {
        "ServerlessDeploymentBucketName": {
          "Value": "serverless-framework-deployments-us-east-1-dfa1c07b-f991",
          "Export": {
            "Name": "sls-flashdash-backend-dev-ServerlessDeploymentBucketName"
          }
        },
        "ApiLambdaFunctionQualifiedArn": {
          "Description": "Current Lambda function version",
          "Value": {
            "Ref": "ApiLambdaVersionnIg7rUSI5PI9frwc5assAh5NvKEkEmlFYrnKGATxM"
          },
          "Export": {
            "Name": "sls-flashdash-backend-dev-ApiLambdaFunctionQualifiedArn"
          }
        },
        "ServiceEndpoint": {
          "Description": "URL of the service endpoint",
          "Value": {
            "Fn::Join": [
              "",
              [
                "https://",
                {
                  "Ref": "ApiGatewayRestApi"
                },
                ".execute-api.",
                {
                  "Ref": "AWS::Region"
                },
                ".",
                {
                  "Ref": "AWS::URLSuffix"
                },
                "/dev"
              ]
            ]
          },
          "Export": {
            "Name": "sls-flashdash-backend-dev-ServiceEndpoint"
          }
        }
      }
    }
  }
}